Workbook

Sheet Inputs
A1: Inputs – Current Policy (2025) | Spain vs France (Sector Averages)
A2: Item | B2: Value | C2: Notes
A3: Base Year Revenue (Spain) | B3: 3900 | C3: €m
A4: Base Year Revenue (France) | B4: 4200 | C4: €m
A5: EBITDA Margin (Spain) | B5: 0.09 | C5: EBITDA / Revenue
A6: EBITDA Margin (France) | B6: 0.11 | C6: EBITDA / Revenue
A7: Starting €/MWh (Spain) | B7: 65 | C7: €/MWh (industrial)
A8: Starting €/MWh (France) | B8: 55 | C8: €/MWh (industrial)
A9: Energy Price CAGR 5Y – Spain (policy) | B9: 0.025 | C9: CAGR €/MWh ES política actual
A10: Energy Price CAGR 5Y – France (policy) | B10: 0.01 | C10: CAGR €/MWh FR política actual
A11: EBITDA Sensitivity to +10€/MWh (Spain) | B11: 0.025 | C11: impacto por +10 €/MWh
A12: EBITDA Sensitivity to +10€/MWh (France) | B12: 0.025 | C12: impacto por +10 €/MWh
A13: Revenue CAGR 5Y – Spain | B13: 0.038 | C13: crecimiento ventas
A14: Revenue CAGR 5Y – France | B14: 0.04 | C14: crecimiento ventas
... A19: Exit EV/EBITDA Multiple | B19: 7 | C19: múltiplo terminal

Sheet Projection_5Y
A1: 5-Year Projection – Current Policy (Spain vs France)
A2: Year | B2: Country | C2: Revenue | D2: €/MWh | E2: EBITDA Margin | F2: EBITDA | G2: Capex | H2: ΔNWC | I2: FCF
A3: 1 | B3: Spain | C3: =Inputs!B3*(1+Inputs!B13)^A3 -> 4048.2 | D3: =Inputs!B7*(1+Inputs!B9)^A3 -> 66.625 | E3: =Inputs!B5 - ((D3-Inputs!B7)/10)*Inputs!B11 -> 0.0859375 | F3: =C3*E3 -> 347.89219 | G3: =C3*Inputs!B15 -> 161.928 | H3: =C3*Inputs!B16 -> 40.482 | I3: =F3*(1-Inputs!B17) - G3 - H3 -> 58.509141
A4: 2 | B4: Spain | C4: =Inputs!B3*(1+Inputs!B13)^A4 -> 4202.0316 | D4: =Inputs!B7*(1+Inputs!B9)^A4 -> 68.290625 | E4: =Inputs!B5 - ((D4-Inputs!B7)/10)*Inputs!B11 -> 0.081773438 | F4: =C4*E4 -> 343.61457 | G4: =C4*Inputs!B15 -> 168.08126 | H4: =C4*Inputs!B16 -> 42.020316 | I4: =F4*(1-Inputs!B17) - G4 - H4 -> 47.609346
A5: 3 | B5: Spain | C5: =Inputs!B3*(1+Inputs!B13)^A5 -> 4361.7088 | D5: =Inputs!B7*(1+Inputs!B9)^A5 -> 69.997891 | E5: =Inputs!B5 - ((D5-Inputs!B7)/10)*Inputs!B11 -> 0.077505273 | F5: =C5*E5 -> 338.05543 | G5: =C5*Inputs!B15 -> 174.46835 | H5: =C5*Inputs!B16 -> 43.617088 | I5: =F5*(1-Inputs!B17) - G5 - H5 -> 35.456135
A6: 4 | B6: Spain | C6: =Inputs!B3*(1+Inputs!B13)^A6 -> 4527.4537 | D6: =Inputs!B7*(1+Inputs!B9)^A6 -> 71.747838 | E6: =Inputs!B5 - ((D6-Inputs!B7)/10)*Inputs!B11 -> 0.073130405 | F6: =C6*E6 -> 331.09453 | G6: =C6*Inputs!B15 -> 181.09815 | H6: =C6*Inputs!B16 -> 45.274537 | I6: =F6*(1-Inputs!B17) - G6 - H6 -> 21.948208
A7: 5 | B7: Spain | C7: =Inputs!B3*(1+Inputs!B13)^A7 -> 4699.497 | D7: =Inputs!B7*(1+Inputs!B9)^A7 -> 73.541534 | E7: =Inputs!B5 - ((D7-Inputs!B7)/10)*Inputs!B11 -> 0.068646165 | F7: =C7*E7 -> 322.60245 | G7: =C7*Inputs!B15 -> 187.97988 | H7: =C7*Inputs!B16 -> 46.99497 | I7: =F7*(1-Inputs!B17) - G7 - H7 -> 6.9769863
A8: 1 | B8: France | C8: =Inputs!B4*(1+Inputs!B14)^A8 -> 4368 | D8: =Inputs!B8*(1+Inputs!B10)^A8 -> 55.55 | E8: =Inputs!B6 - ((D8-Inputs!B8)/10)*Inputs!B12 -> 0.108625 | F8: =C8*E8 -> 474.474 | G8: =C8*Inputs!B15 -> 174.72 | H8: =C8*Inputs!B16 -> 43.68 | I8: =F8*(1-Inputs!B17) - G8 - H8 -> 137.4555
A9: 2 | B9: France | C9: =Inputs!B4*(1+Inputs!B14)^A9 -> 4542.72 | D9: =Inputs!B8*(1+Inputs!B10)^A9 -> 56.1055 | E9: =Inputs!B6 - ((D9-Inputs!B8)/10)*Inputs!B12 -> 0.10723625 | F9: =C9*E9 -> 487.14426 | G9: =C9*Inputs!B15 -> 181.7088 | H9: =C9*Inputs!B16 -> 45.4272 | I9: =F9*(1-Inputs!B17) - G9 - H9 -> 138.22219
A10: 3 | B10: France | C10: =Inputs!B4*(1+Inputs!B14)^A10 -> 4724.4288 | D10: =Inputs!B8*(1+Inputs!B10)^A10 -> 56.666555 | E10: =Inputs!B6 - ((D10-Inputs!B8)/10)*Inputs!B12 -> 0.10583361 | F10: =C10*E10 -> 500.00337 | G10: =C10*Inputs!B15 -> 188.97715 | H10: =C10*Inputs!B16 -> 47.244288 | I10: =F10*(1-Inputs!B17) - G10 - H10 -> 138.78109
A11: 4 | B11: France | C11: =Inputs!B4*(1+Inputs!B14)^A11 -> 4913.406 | D11: =Inputs!B8*(1+Inputs!B10)^A11 -> 57.233221 | E11: =Inputs!B6 - ((D11-Inputs!B8)/10)*Inputs!B12 -> 0.10441695 | F11: =C11*E11 -> 513.04286 | G11: =C11*Inputs!B15 -> 196.53624 | H11: =C11*Inputs!B16 -> 49.13406 | I11: =F11*(1-Inputs!B17) - G11 - H11 -> 139.11185
A12: 5 | B12: France | C12: =Inputs!B4*(1+Inputs!B14)^A12 -> 5109.9422 | D12: =Inputs!B8*(1+Inputs!B10)^A12 -> 57.805553 | E12: =Inputs!B6 - ((D12-Inputs!B8)/10)*Inputs!B12 -> 0.10298612 | F12: =C12*E12 -> 526.25311 | G12: =C12*Inputs!B15 -> 204.39769 | H12: =C12*Inputs!B16 -> 51.099422 | I12: =F12*(1-Inputs!B17) - G12 - H12 -> 139.19272

Sheet DCF
A1: DCF – Unlevered (Current Policy)
A2: Country | B2: WACC | C2: Tax Rate | D2: PV(FCF) | E2: Exit EV/EBITDA | F2: EBITDA (Y5) | G2: Terminal Value | H2: PV(Terminal) | I2: Enterprise Value
A3: Spain | B3: =Inputs!B18 -> 0.09 | C3: =Inputs!B17 -> 0.25 | D3: =SUM(Projection_5Y!I3/(1+$B$3)^1+Projection_5Y!I4/(1+$B$3)^2+Projection_5Y!I5/(1+$B$3)^3+Projection_5Y!I6/(1+$B$3)^4+Projection_5Y!I7/(1+$B$3)^5) -> 141.21181 | E3: =Inputs!B19 -> 7 | F3: =Projection_5Y!F7 -> 322.60245 | G3: =E3*F3 -> 2258.2171 | H3: =G3/(1+$B$3)^5 -> 1467.6862 | I3: =D3+H3 -> 1608.898
A4: France | B4: =Inputs!B18 -> 0.09 | C4: =Inputs!B17 -> 0.25 | D4: =SUM(Projection_5Y!I8/(1+$B$4)^1+Projection_5Y!I9/(1+$B$4)^2+Projection_5Y!I10/(1+$B$4)^3+Projection_5Y!I11/(1+$B$4)^4+Projection_5Y!I12/(1+$B$4)^5) -> 538.62534 | E4: =Inputs!B19 -> 7 | F4: =Projection_5Y!F12 -> 526.25311 | G4: =E4*F4 -> 3683.7718 | H4: =G4/(1+$B$4)^5 -> 2394.1989 | I4: =D4+H4 -> 2932.8242

Sheet WEDGE
A1: Wedge de coste eléctrico y compresión de margen (ES vs FR)
A2: Year | B2: €/MWh ES | C2: €/MWh FR | D2: Wedge €/MWh (ES-FR) | E2: Base Margin ES | F2: Base Margin FR | G2: Proj Margin ES | H2: Proj Margin FR | I2: Margin Gap (ES-FR) | J2: Revenue ES | K2: EBITDA Loss ES vs FR (€/m)
A3: 1 | B3: =Projection_5Y!D3 -> 66.625 | C3: =Projection_5Y!D8 -> 55.55 | D3: =B3-C3 -> 11.075 | E3: =Inputs!B5 -> 0.09 | F3: =Inputs!B6 -> 0.11 | G3: =Projection_5Y!E3 -> 0.0859375 | H3: =Projection_5Y!E8 -> 0.108625 | I3: =G3-H3 -> -0.0226875 | J3: =Projection_5Y!C3 -> 4048.2 | K3: =MAX(0,H3-G3)*J3 -> 91.843538
A4: 2 | B4: =Projection_5Y!D4 -> 68.290625 | C4: =Projection_5Y!D9 -> 56.1055 | D4: =B4-C4 -> 12.185125 | E4: =Inputs!B5 -> 0.09 | F4: =Inputs!B6 -> 0.11 | G4: =Projection_5Y!E4 -> 0.081773438 | H4: =Projection_5Y!E9 -> 0.10723625 | I4: =G4-H4 -> -0.025462812 | J4: =Projection_5Y!C4 -> 4202.0316 | K4: =MAX(0,H4-G4)*J4 -> 106.99554
A5: 3 | B5: =Projection_5Y!D5 -> 69.997891 | C5: =Projection_5Y!D10 -> 56.666555 | D5: =B5-C5 -> 13.331336 | E5: =Inputs!B5 -> 0.09 | F5: =Inputs!B6 -> 0.11 | G5: =Projection_5Y!E5 -> 0.077505273 | H5: =Projection_5Y!E10 -> 0.10583361 | I5: =G5-H5 -> -0.028328339 | J5: =Projection_5Y!C5 -> 4361.7088 | K5: =MAX(0,H5-G5)*J5 -> 123.55997
A6: 4 | B6: =Projection_5Y!D6 -> 71.747838 | C6: =Projection_5Y!D11 -> 57.233221 | D6: =B6-C6 -> 14.514617 | E6: =Inputs!B5 -> 0.09 | F6: =Inputs!B6 -> 0.11 | G6: =Projection_5Y!E6 -> 0.073130405 | H6: =Projection_5Y!E11 -> 0.10441695 | I6: =G6-H6 -> -0.031286543 | J6: =Projection_5Y!C6 -> 4527.4537 | K6: =MAX(0,H6-G6)*J6 -> 141.64838
A7: 5 | B7: =Projection_5Y!D7 -> 73.541534 | C7: =Projection_5Y!D12 -> 57.805553 | D7: =B7-C7 -> 15.735981 | E7: =Inputs!B5 -> 0.09 | F7: =Inputs!B6 -> 0.11 | G7: =Projection_5Y!E7 -> 0.068646165 | H7: =Projection_5Y!E12 -> 0.10298612 | I7: =G7-H7 -> -0.034339953 | J7: =Projection_5Y!C7 -> 4699.497 | K7: =MAX(0,H7-G7)*J7 -> 161.3805
J9: Total EBITDA Loss ES (€/m) | K9: =SUM(K3:K7) -> 625.42793

Sheet PARAMS
A1: Parámetros de competitividad y empleo
A2: Item | B2: Value | C2: Notes | E2: Derived (selected year)
A3: Year_Selected (1..5) | B3: 5 | C3: Año de referencia para competitividad | E3: ES Proj Margin (sel) | F3: =INDEX(WEDGE!G3:G7, B3) -> 0.068646165
A4: PassThrough_to_Price (0..1) | B4: 0.3 | C4: Parte del gap de coste que se traslada a precio | E4: FR Proj Margin (sel) | F4: =INDEX(WEDGE!H3:H7, B3) -> 0.10298612
A5: Elasticity_Price_to_Share | B5: -0.3 | C5: Elasticidad de cuota ante diferencial de precio | E5: Cost Gap % of Revenue | F5: =MAX(0, F4 - F3) -> 0.034339953
A6: Direct_Jobs_per_€m_Sales | B6: 4 | C6: Empleo directo por €m de ventas | E6: Price Delta % | F6: =B4*F5 -> 0.010301986
A7: Indirect_Multiplier | B7: 1.8 | C7: Multiplicador indirecto/inducido

Sheet FLOWS
A1: Flujos por mercado y subsegmento (rellenar datos)
A2: País | B2: Sector | C2: MarketSize_€m (Importaciones 2024) | D2: ES_Sales_€m | E2: FR_Sales_€m | G2: Total ES Sales | H2: Total FR Sales
A3: Germany | B3: Aluminio | C3: 8200 | D3: 880 | E3: 1250 | G3: =SUM(D3:D9997) -> 5786.6 | H3: =SUM(E3:E9997) -> 7306
A4: Italy | B4: Aluminio | C4: 6300 | D4: 760 | E4: 900
A5: Netherlands | B5: Aluminio | C5: 3400 | D5: 290 | E5: 510
A6: Belgium | B6: Aluminio | C6: 2600 | D6: 220 | E6: 430
A7: Poland | B7: Aluminio | C7: 2300 | D7: 200 | E7: 260
A8: Czechia | B8: Aluminio | C8: 1600 | D8: 130 | E8: 170
A9: France | B9: Aluminio | C9: 5200 | D9: 370 | E9: 2100
A10: Spain | B10: Aluminio | C10: 3900 | D10: 2100 | E10: 420
A11: Germany | B11: Acerías eléctricas | C11: 1600 | D11: 143 | E11: 230
A12: Italy | B12: Acerías eléctricas | C12: 1400 | D12: 132 | E12: 190
A13: Netherlands | B13: Acerías eléctricas | C13: 750 | D13: 75 | E13: 125
A14: Belgium | B14: Acerías eléctricas | C14: 550 | D14: 51 | E14: 105
A15: Poland | B15: Acerías eléctricas | C15: 450 | D15: 44 | E15: 58
... A18: Spain | B18: Acerías eléctricas | C18: 1000 | D18: 300 | E18: 120

Sheet OVERLAP
A1: Solapamiento competitivo y ventas perdidas (ES)
A2: País | B2: Sector | C2: MarketSize_€m | D2: ES_Sales_€m | E2: FR_Sales_€m | F2: ES_Share | G2: FR_Share | H2: OverlapShare | I2: PriceDeltaPct (sel) | J2: ShareLossFactor | K2: Lost_ES_Sales_€m | L2: Contribution_to_ES_% | N2: Total ES Sales | O2: =FLOWS!$G$3 -> 5786.6
A3: Germany | B3: Aluminio | C3: =FLOWS!C3 -> 8200 | D3: =FLOWS!D3 -> 880 | E3: =FLOWS!E3 -> 1250 | F3: =IFERROR(D3/C3,0) -> 0.10731707 | G3: =IFERROR(E3/C3,0) -> 0.15243902 | H3: =MIN(F3,G3) -> 0.10731707 | I3: =PARAMS!F6 -> 0.010301986 | J3: =H3 * (-PARAMS!B4) * I3 -> -0.00033167369 | K3: =D3 * J3 -> -0.29187285 | L3: =IFERROR(K3/FLOWS!$G$3,0) -> -5.0439437e-05 | N3: Total Lost ES Sales (€/m) | O3: =SUM(K3:K9995) -> -1.834085
A4: Italy | B4: Aluminio | C4: =FLOWS!C4 -> 6300 | D4: =FLOWS!D4 -> 760 | E4: =FLOWS!E4 -> 900 | F4: =IFERROR(D4/C4,0) -> 0.12063492 | G4: =IFERROR(E4/C4,0) -> 0.14285714 | H4: =MIN(F4,G4) -> 0.12063492 | I4: =PARAMS!F6 -> 0.010301986 | J4: =H4 * (-PARAMS!B4) * I4 -> -0.00037283377 | K4: =D4 * J4 -> -0.28335367 | L4: =IFERROR(K4/FLOWS!$G$3,0) -> -4.8967212e-05 | N4: % ES en competencia directa (avg overlap) | O4: =AVERAGE(H3:H9995) -> 0.092333865
A5: Netherlands | B5: Aluminio | C5: =FLOWS!C5 -> 3400 | D5: =FLOWS!D5 -> 290 | E5: =FLOWS!E5 -> 510 | F5: =IFERROR(D5/C5,0) -> 0.085294118 | G5: =IFERROR(E5/C5,0) -> 0.15 | H5: =MIN(F5,G5) -> 0.085294118 | I5: =PARAMS!F6 -> 0.010301986 | J5: =H5 * (-PARAMS!B4) * I5 -> -0.00026360964 | K5: =D5 * J5 -> -0.076446795 | L5: =IFERROR(K5/FLOWS!$G$3,0) -> -1.3211004e-05 | N5: % de ventas ES potencialmente perdidas | O5: =IFERROR(O3/O2,0) -> -0.00031695383
A6: Belgium | B6: Aluminio | C6: =FLOWS!C6 -> 2600 | D6: =FLOWS!D6 -> 220 | E6: =FLOWS!E6 -> 430 | F6: =IFERROR(D6/C6,0) -> 0.084615385 | G6: =IFERROR(E6/C6,0) -> 0.16538462 | H6: =MIN(F6,G6) -> 0.084615385 | I6: =PARAMS!F6 -> 0.010301986 | J6: =H6 * (-PARAMS!B4) * I6 -> -0.00026151195 | K6: =D6 * J6 -> -0.057532628 | L6: =IFERROR(K6/FLOWS!$G$3,0) -> -9.942389e-06
A7: Poland | B7: Aluminio | C7: =FLOWS!C7 -> 2300 | D7: =FLOWS!D7 -> 200 | E7: =FLOWS!E7 -> 260 | F7: =IFERROR(D7/C7,0) -> 0.086956522 | G7: =IFERROR(E7/C7,0) -> 0.11304348 | H7: =MIN(F7,G7) -> 0.086956522 | I7: =PARAMS!F6 -> 0.010301986 | J7: =H7 * (-PARAMS!B4) * I7 -> -0.00026874746 | K7: =D7 * J7 -> -0.053749491 | L7: =IFERROR(K7/FLOWS!$G$3,0) -> -9.2886136e-06
A8: Czechia | B8: Aluminio | C8: =FLOWS!C8 -> 1600 | D8: =FLOWS!D8 -> 130 | E8: =FLOWS!E8 -> 170 | F8: =IFERROR(D8/C8,0) -> 0.08125 | G8: =IFERROR(E8/C8,0) -> 0.10625 | H8: =MIN(F8,G8) -> 0.08125 | I8: =PARAMS!F6 -> 0.010301986 | J8: =H8 * (-PARAMS!B4) * I8 -> -0.0002511109 | K8: =D8 * J8 -> -0.032644418 | L8: =IFERROR(K8/FLOWS!$G$3,0) -> -5.6413814e-06
A9: France | B9: Aluminio | C9: =FLOWS!C9 -> 5200 | D9: =FLOWS!D9 -> 370 | E9: =FLOWS!E9 -> 2100 | F9: =IFERROR(D9/C9,0) -> 0.071153846 | G9: =IFERROR(E9/C9,0) -> 0.40384615 | H9: =MIN(F9,G9) -> 0.071153846 | I9: =PARAMS!F6 -> 0.010301986 | J9: =H9 * (-PARAMS!B4) * I9 -> -0.00021990777 | K9: =D9 * J9 -> -0.081365876 | L9: =IFERROR(K9/FLOWS!$G$3,0) -> -1.4061085e-05
A10: Spain | B10: Aluminio | C10: =FLOWS!C10 -> 3900 | D10: =FLOWS!D10 -> 2100 | E10: =FLOWS!E10 -> 420 | F10: =IFERROR(D10/C10,0) -> 0.53846154 | G10: =IFERROR(E10/C10,0) -> 0.10769231 | H10: =MIN(F10,G10) -> 0.10769231 | I10: =PARAMS!F6 -> 0.010301986 | J10: =H10 * (-PARAMS!B4) * I10 -> -0.00033283339 | K10: =D10 * J10 -> -0.69895011 | L10: =IFERROR(K10/FLOWS!$G$3,0) -> -0.0001207877
A11: Germany | B11: Acerías eléctricas | C11: =FLOWS!C11 -> 1600 | D11: =FLOWS!D11 -> 143 | E11: =FLOWS!E11 -> 230 | F11: =IFERROR(D11/C11,0) -> 0.089375 | G11: =IFERROR(E11/C11,0) -> 0.14375 | H11: =MIN(F11,G11) -> 0.089375 | I11: =PARAMS!F6 -> 0.010301986 | J11: =H11 * (-PARAMS!B4) * I11 -> -0.00027622199 | K11: =D11 * J11 -> -0.039499745 | L11: =IFERROR(K11/FLOWS!$G$3,0) -> -6.8260715e-06
A12: Italy | B12: Acerías eléctricas | C12: =FLOWS!C12 -> 1400 | D12: =FLOWS!D12 -> 132 | E12: =FLOWS!E12 -> 190 | F12: =IFERROR(D12/C12,0) -> 0.094285714 | G12: =IFERROR(E12/C12,0) -> 0.13571429 | H12: =MIN(F12,G12) -> 0.094285714 | I12: =PARAMS!F6 -> 0.010301986 | J12: =H12 * (-PARAMS!B4) * I12 -> -0.00029139903 | K12: =D12 * J12 -> -0.038464672 | L12: =IFERROR(K12/FLOWS!$G$3,0) -> -6.6471972e-06
A13: Netherlands | B13: Acerías eléctricas | C13: =FLOWS!C13 -> 750 | D13: =FLOWS!D13 -> 75 | E13: =FLOWS!E13 -> 125 | F13: =IFERROR(D13/C13,0) -> 0.1 | G13: =IFERROR(E13/C13,0) -> 0.16666667 | H13: =MIN(F13,G13) -> 0.1 | I13: =PARAMS!F6 -> 0.010301986 | J13: =H13 * (-PARAMS!B4) * I13 -> -0.00030905957 | K13: =D13 * J13 -> -0.023179468 | L13: =IFERROR(K13/FLOWS!$G$3,0) -> -4.0057146e-06
A14: Belgium | B14: Acerías eléctricas | C14: =FLOWS!C14 -> 550 | D14: =FLOWS!D14 -> 51 | E14: =FLOWS!E14 -> 105 | F14: =IFERROR(D14/C14,0) -> 0.092727273 | G14: =IFERROR(E14/C14,0) -> 0.19090909 | H14: =MIN(F14,G14) -> 0.092727273 | I14: =PARAMS!F6 -> 0.010301986 | J14: =H14 * (-PARAMS!B4) * I14 -> -0.00028658251 | K14: =D14 * J14 -> -0.014615708 | L14: =IFERROR(K14/FLOWS!$G$3,0) -> -2.5257851e-06
A15: Poland | B15: Acerías eléctricas | C15: =FLOWS!C15 -> 450 | D15: =FLOWS!D15 -> 44 | E15: =FLOWS!E15 -> 58 | F15: =IFERROR(D15/C15,0) -> 0.097777778 | G15: =IFERROR(E15/C15,0) -> 0.12888889 | H15: =MIN(F15,G15) -> 0.097777778 | I15: =PARAMS!$F$6 -> 0.010301986 | J15: =H15 * (-PARAMS!$B$4) * I15 -> -0.00030219158 | K15: =D15 * J15 -> -0.01329643 | L15: =IFERROR(K15/FLOWS!$G$3,0) -> -2.2977966e-06
A16: Czechia | B16: Acerías eléctricas | C16: =FLOWS!C16 -> 350 | D16: =FLOWS!D16 -> 30.6 | E16: =FLOWS!E16 -> 38 | F16: =IFERROR(D16/C16,0) -> 0.087428571 | G16: =IFERROR(E16/C16,0) -> 0.10857143 | H16: =MIN(F16,G16) -> 0.087428571 | I16: =PARAMS!$F$6 -> 0.010301986 | J16: =H16 * (-PARAMS!$B$4) * I16 -> -0.00027020637 | K16: =D16 * J16 -> -0.0082683149 | L16: =IFERROR(K16/FLOWS!$G$3,0) -> -1.4288727e-06
A17: France | B17: Acerías eléctricas | C17: =FLOWS!C17 -> 1200 | D17: =FLOWS!D17 -> 61 | E17: =FLOWS!E17 -> 400 | F17: =IFERROR(D17/C17,0) -> 0.050833333 | G17: =IFERROR(E17/C17,0) -> 0.33333333 | H17: =MIN(F17,G17) -> 0.050833333 | I17: =PARAMS!$F$6 -> 0.010301986 | J17: =H17 * (-PARAMS!$B$4) * I17 -> -0.00015710528 | K17: =D17 * J17 -> -0.0095834223 | L17: =IFERROR(K17/FLOWS!$G$3,0) -> -1.6561404e-06
A18: Spain | B18: Acerías eléctricas | C18: =FLOWS!C18 -> 1000 | D18: =FLOWS!D18 -> 300 | E18: =FLOWS!E18 -> 120 | F18: =IFERROR(D18/C18,0) -> 0.3 | G18: =IFERROR(E18/C18,0) -> 0.12 | H18: =MIN(F18,G18) -> 0.12 | I18: =PARAMS!$F$6 -> 0.010301986 | J18: =H18 * (-PARAMS!$B$4) * I18 -> -0.00037087149 | K18: =D18 * J18 -> -0.11126145 | L18: =IFERROR(K18/FLOWS!$G$3,0) -> -1.922743e-05

Sheet EMPLOYMENT_MARGIN
A1: Empleo afectado por bajada de margen EBITDA (aprox.)
A2: Metric | B2: Value | C2: Notes
A3: Year Selected | B3: 5 | C3: Año para el cálculo (PARAMS)
A4: Revenue ES (sel, €m) | B4: 4699.497 | C4: Ingresos ES en el año seleccionado
A5: Base Margin ES | B5: 0.09 | C5: Margen EBITDA base ES
A6: Proj Margin ES (sel) | B6: 0.081080652 | C6: Margen EBITDA proyectado ES (ajustado por energía)
A7: Margin Delta (Base - Proj) | B7: =MAX(0,B5-B6) -> 0.0089193482 | C7: Pérdida de margen en puntos porcentuales
A8: EBITDA Loss (€/m) | B8: =B4*B7 -> 41.91645 | C8: Ingresos × Delta de margen
A9: Share of EBITDA Loss → Volume | B9: 1.8 | C9: Proporción que se traslada a menor volumen/empleo
A10: Sales-Equivalent Loss (€/m) | B10: =IF(B6>0, B8/B6*B9, 0) -> 930.55011 | C10: Convierte pérdida EBITDA a ventas equivalentes afectadas
A11: Direct Jobs per €m Sales | B11: 4 | C11: Empleo directo por €m de ventas
A12: Indirect Multiplier | B12: 1.8 | C12: Multiplicador indirecto/inducido
A13: Direct Jobs Lost (margin effect) | B13: =B10*B11 -> 3722.2004 | C13: Empleo directo asociado a la pérdida por margen
A14: Total Jobs Lost (margin effect) | B14: =B12*B13 -> 6699.9608 | C14: Total (directo + indirecto)

Sheet EMPLOYMENT_SALES
A1: Empleo afectado por pérdida de ventas (estimación)
A2: Metric | B2: Value | C2: Notes
A3: Lost ES Sales (€/m) | B3: =- OVERLAP!O3 -> 1.834085 | C3: Ventas españolas potencialmente perdidas
A4: Direct Jobs per €m Sales | B4: =PARAMS!B6 -> 4 | C4: Dato editable
A5: Indirect Multiplier | B5: =PARAMS!B7 -> 1.8 | C5: Efecto indirecto/inducido
A6: Direct Jobs Lost | B6: =B3*B4 -> 7.3363402 | C6: Empleo directo afectado
A7: Total Jobs Lost (Direct x Multiplier) | B7: =B5*B6 -> 13.205412 | C7: Impacto total

Sheet TOTAL_EMPLOYMENT
A2: Jobs Lost (Sales effect) | B2: =EMPLOYMENT_SALES!B7 -> 13.205412
A3: Jobs Lost (margin effect) | B3: =EMPLOYMENT_MARGIN!B14 -> 6699.9608
A4: Total Jobs Lost | B4: =SUM(B2:B3) -> 6713.1662
